{
  "packageDirectories": [
    {
      "path": "force-app",
      "default": true,
      "package": "usernavi",
      "versionName": "UserNavi V1.1.0",
      "versionNumber": "1.1.0.NEXT"
    },
    {
      "versionName": "ver 0.1",
      "versionNumber": "0.1.0.NEXT",
      "path": "force-app",
      "default": false,
      "package": "LWCPermissionNavigator",
      "versionDescription": ""
    }
  ],
  "namespace": "",
  "sfdcLoginUrl": "https://login.salesforce.com",
  "sourceApiVersion": "45.0",
  "packageAliases": {
    "usernavi": "0HoB0000000TN31KAG",
    "usernavi@1.0.0-1": "04tB0000000PdTZIA0",
    "usernavi@1.0.1-1": "04tB0000000AKbkIAG",
    "usernavi@1.0.2-1": "04tB0000000AKbpIAG",
    "usernavi@1.0.3-2": "04tB00000006l4sIAA",
    "usernavi@1.1.0-1": "04tB00000006l4xIAA",
    "LWCPermissionNavigator": "0HoWs00000018DFKAY"
  }
}